CHANGES.txt
LICENSE.txt
MANIFEST.in
README.txt
setup.cfg
setup.py
PufferFish.egg-info/PKG-INFO
PufferFish.egg-info/SOURCES.txt
PufferFish.egg-info/dependency_links.txt
PufferFish.egg-info/requires.txt
PufferFish.egg-info/top_level.txt
pufferfish/__init__.py
pufferfish/exc.py
pufferfish/fsentity.py
tests/__init__.py
tests/test_file.py
tests/model/__init__.py
tests/model/base.py
tests/model/exc.py
tests/model/file.py
tests/model/image.py