Metadata-Version: 1.0
Name: PufferFish
Version: 0.2
Summary: SQLAlchemy session extension
Home-page: http://code.asidev.net/pufferfish/
Author: Giacomo Bagnoli
Author-email: g.bagnoli@asidev.com
License: LICENSE.txt
Platform: UNKNOWN
Classifier: Development Status :: 3 - Beta
Classifier: Intended Audience :: Developers
Classifier: License :: OSI Approved :: MIT License
Classifier: Programming Language :: Python
Classifier: Topic :: Database :: Front-Ends
Classifier: Topic :: Software Development :: Libraries :: Python Modules
